kicad_mcp/__init__.py
kicad_mcp/config.py
kicad_mcp/context.py
kicad_mcp/server.py
kicad_mcp/prompts/__init__.py
kicad_mcp/prompts/bom_prompts.py
kicad_mcp/prompts/drc_prompt.py
kicad_mcp/prompts/pattern_prompts.py
kicad_mcp/prompts/templates.py
kicad_mcp/resources/__init__.py
kicad_mcp/resources/bom_resources.py
kicad_mcp/resources/drc_resources.py
kicad_mcp/resources/files.py
kicad_mcp/resources/netlist_resources.py
kicad_mcp/resources/pattern_resources.py
kicad_mcp/resources/projects.py
kicad_mcp/tools/__init__.py
kicad_mcp/tools/analysis_tools.py
kicad_mcp/tools/bom_tools.py
kicad_mcp/tools/drc_tools.py
kicad_mcp/tools/export_tools.py
kicad_mcp/tools/netlist_tools.py
kicad_mcp/tools/pattern_tools.py
kicad_mcp/tools/project_tools.py
kicad_mcp/tools/validation_tools.py
kicad_mcp/tools/drc_impl/__init__.py
kicad_mcp/tools/drc_impl/cli_drc.py
kicad_mcp/utils/__init__.py
kicad_mcp/utils/boundary_validator.py
kicad_mcp/utils/component_utils.py
kicad_mcp/utils/drc_history.py
kicad_mcp/utils/env.py
kicad_mcp/utils/file_utils.py
kicad_mcp/utils/kicad_api_detection.py
kicad_mcp/utils/kicad_cli.py
kicad_mcp/utils/kicad_utils.py
kicad_mcp/utils/netlist_parser.py
kicad_mcp/utils/path_validator.py
kicad_mcp/utils/pattern_recognition.py
kicad_mcp/utils/secure_subprocess.py
kicad_mcp/utils/temp_dir_manager.py
iflow_mcp_kicad_mcp-0.1.0.dist-info/METADATA
iflow_mcp_kicad_mcp-0.1.0.dist-info/WHEEL
iflow_mcp_kicad_mcp-0.1.0.dist-info/entry_points.txt
iflow_mcp_kicad_mcp-0.1.0.dist-info/licenses/LICENSE
iflow_mcp_kicad_mcp-0.1.0.dist-info/RECORD
