Metadata-Version: 2.4
Name: iflow-mcp_kicad-mcp
Version: 0.1.0
Summary: Model Context Protocol (MCP) server for KiCad electronic design automation (EDA) files
Project-URL: Homepage, https://github.com/lamaalrajih/kicad-mcp
Project-URL: Bug Tracker, https://github.com/lamaalrajih/kicad-mcp/issues
Project-URL: Documentation, https://github.com/lamaalrajih/kicad-mcp#readme
Author: KiCad MCP Contributors
Maintainer: KiCad MCP Contributors
License: MIT
License-File: LICENSE
Keywords: ai,assistant,eda,electronics,kicad,mcp,model-context-protocol,pcb,schematic
Classifier: Development Status :: 4 - Beta
Classifier: Intended Audience :: Developers
Classifier: Intended Audience :: Manufacturing
Classifier: License :: OSI Approved :: MIT License
Classifier: Operating System :: OS Independent
Classifier: Programming Language :: Python :: 3
Classifier: Programming Language :: Python :: 3.10
Classifier: Programming Language :: Python :: 3.11
Classifier: Programming Language :: Python :: 3.12
Classifier: Programming Language :: Python :: 3.13
Classifier: Topic :: Scientific/Engineering :: Electronic Design Automation (EDA)
Classifier: Topic :: Software Development :: Libraries :: Python Modules
Classifier: Typing :: Typed
Requires-Python: >=3.10
Requires-Dist: defusedxml>=0.7.0
Requires-Dist: fastmcp>=2.0.0
Requires-Dist: mcp[cli]>=1.0.0
Requires-Dist: pandas>=2.0.0
Requires-Dist: pyyaml>=6.0.0
